agent_skills_mcp/__init__.py
agent_skills_mcp/enums.py
agent_skills_mcp/interfaces.py
agent_skills_mcp/main.py
agent_skills_mcp/model.py
agent_skills_mcp/scan.py
agent_skills_mcp/server.py
agent_skills_mcp-0.1.3.dist-info/METADATA
agent_skills_mcp-0.1.3.dist-info/WHEEL
agent_skills_mcp-0.1.3.dist-info/entry_points.txt
agent_skills_mcp-0.1.3.dist-info/licenses/LICENSE
agent_skills_mcp-0.1.3.dist-info/RECORD
