Metadata-Version: 2.4
Name: agent-skills-mcp
Version: 0.1.3
Summary: Load Agent Skills for your agents
Project-URL: Homepage, https://github.com/DiscreteTom/agent-skills-mcp
Project-URL: Repository, https://github.com/DiscreteTom/agent-skills-mcp
Project-URL: Issues, https://github.com/DiscreteTom/agent-skills-mcp/issues
Author-email: DiscreteTom <discrete_tom@outlook.com>
License: MIT
License-File: LICENSE
Keywords: agent-skills,mcp,model-context-protocol,tools
Classifier: Intended Audience :: Developers
Classifier: License :: OSI Approved :: MIT License
Classifier: Programming Language :: Python :: 3
Classifier: Programming Language :: Python :: 3.10
Classifier: Programming Language :: Python :: 3.11
Classifier: Programming Language :: Python :: 3.12
Classifier: Programming Language :: Python :: 3.13
Classifier: Topic :: Software Development :: Libraries :: Python Modules
Requires-Python: >=3.10
Requires-Dist: fastmcp>=2.12.4
Requires-Dist: python-frontmatter>=1.1.0
Requires-Dist: typer>=0.20.0
